homescript/__init__.py
homescript-5.2.dist-info/LICENSE
homescript-5.2.dist-info/METADATA
homescript-5.2.dist-info/WHEEL
homescript-5.2.dist-info/top_level.txt
homescript-5.2.dist-info/RECORD
