Metadata-Version: 2.1
Name: homescript
Version: 5.2
Summary: HomeScript CLI: Command Line Control of HomeBridge
Home-page: https://github.com/menahishayan/HomeScript
Author: Menahi Shayan
Author-email: menahi.shayan@gmail.com
License: UNKNOWN
Platform: UNKNOWN
Classifier: Programming Language :: Python :: 3
Classifier: License :: OSI Approved :: GNU General Public License v3 or later (GPLv3+)
Classifier: Operating System :: OS Independent
Requires-Python: >=3.7
Requires-Dist: requests
